foliant/backends/pandoc.py
foliantcontrib.pandoc-1.1.2.dist-info/LICENSE
foliantcontrib.pandoc-1.1.2.dist-info/METADATA
foliantcontrib.pandoc-1.1.2.dist-info/WHEEL
foliantcontrib.pandoc-1.1.2.dist-info/top_level.txt
foliantcontrib.pandoc-1.1.2.dist-info/RECORD
