Metadata-Version: 2.1
Name: foliantcontrib.pandoc
Version: 1.1.2
Summary: Pandoc backend for Foliant doc maker. Produces PDF and DOCX.
Home-page: https://github.com/foliant-docs/foliantcontrib.pandoc
Author: Konstantin Molchanov
Author-email: moigagoo@live.com
License: MIT
Platform: any
Classifier: Development Status :: 5 - Production/Stable
Classifier: Environment :: Console
Classifier: Intended Audience :: Developers
Classifier: License :: OSI Approved :: MIT License
Classifier: Operating System :: OS Independent
Classifier: Programming Language :: Python
Classifier: Topic :: Documentation
Classifier: Topic :: Utilities
Classifier: Programming Language :: Python :: 3.6
License-File: LICENSE
Requires-Dist: foliant (>=1.0.8)
Requires-Dist: foliantcontrib.flatten (>=1.0.2)
Requires-Dist: foliantcontrib.meta (>=1.3.2)
